Metadata-Version: 1.1
Name: real-django-s3
Version: 1.2.1
Summary: A simple API for download and upload graphics resources to/from a Amazon S3 bucket
Home-page: https://github.com/RaydelMiranda/django-s3
Author: Raydel Miranda
Author-email: raydel.miranda.gomez@gmail.com
License: GPL
Keywords: development web django amazon s3
Platform: UNKNOWN
Classifier: Development Status :: 5 - Production/Stable
Classifier: Intended Audience :: Developers
Classifier: Topic :: Software Development
Classifier: License :: OSI Approved :: GNU General Public License v3 (GPLv3)
Classifier: Programming Language :: Python :: 2.7
Classifier: Programming Language :: Python :: 3
Classifier: Programming Language :: Python :: 3.3
Classifier: Programming Language :: Python :: 3.4
Classifier: Programming Language :: Python :: 3.5
